<annotation>
	<folder>splitted_BIDV_data_6</folder>
	<filename>2f47b186-ab5a-49a5-ae6b-72d7ba77367b.jpg</filename>
	<path>/home/lynkenion/Downloads/splitted_BIDV_data_6/2f47b186-ab5a-49a5-ae6b-72d7ba77367b.jpg</path>
	<source>
		<database>Unknown</database>
	</source>
	<size>
		<width>172</width>
		<height>415</height>
		<depth>3</depth>
	</size>
	<segmented>0</segmented>
	<object>
		<name>Lanyard</name>
		<pose>Unspecified</pose>
		<truncated>0</truncated>
		<difficult>0</difficult>
		<bndbox>
			<xmin>46</xmin>
			<ymin>59</ymin>
			<xmax>113</xmax>
			<ymax>106</ymax>
		</bndbox>
	</object>
</annotation>
