<annotation>
	<folder>splitted_BIDV_data_6</folder>
	<filename>2fe0cd18-7b48-4fa3-8893-72ab0f634f1a.jpg</filename>
	<path>/home/lynkenion/Downloads/splitted_BIDV_data_6/2fe0cd18-7b48-4fa3-8893-72ab0f634f1a.jpg</path>
	<source>
		<database>Unknown</database>
	</source>
	<size>
		<width>150</width>
		<height>498</height>
		<depth>3</depth>
	</size>
	<segmented>0</segmented>
	<object>
		<name>Lanyard</name>
		<pose>Unspecified</pose>
		<truncated>0</truncated>
		<difficult>0</difficult>
		<bndbox>
			<xmin>15</xmin>
			<ymin>91</ymin>
			<xmax>63</xmax>
			<ymax>191</ymax>
		</bndbox>
	</object>
	<object>
		<name>ID_CARD</name>
		<pose>Unspecified</pose>
		<truncated>0</truncated>
		<difficult>0</difficult>
		<bndbox>
			<xmin>20</xmin>
			<ymin>194</ymin>
			<xmax>51</xmax>
			<ymax>229</ymax>
		</bndbox>
	</object>
</annotation>
