<annotation>
	<folder>splitted_BIDV_data_6</folder>
	<filename>2fec93cf-0510-4523-b077-58b733c20c5e.jpg</filename>
	<path>/home/lynkenion/Downloads/splitted_BIDV_data_6/2fec93cf-0510-4523-b077-58b733c20c5e.jpg</path>
	<source>
		<database>Unknown</database>
	</source>
	<size>
		<width>379</width>
		<height>902</height>
		<depth>3</depth>
	</size>
	<segmented>0</segmented>
	<object>
		<name>Lanyard</name>
		<pose>Unspecified</pose>
		<truncated>0</truncated>
		<difficult>0</difficult>
		<bndbox>
			<xmin>231</xmin>
			<ymin>205</ymin>
			<xmax>331</xmax>
			<ymax>392</ymax>
		</bndbox>
	</object>
	<object>
		<name>ID_CARD</name>
		<pose>Unspecified</pose>
		<truncated>0</truncated>
		<difficult>0</difficult>
		<bndbox>
			<xmin>251</xmin>
			<ymin>386</ymin>
			<xmax>293</xmax>
			<ymax>466</ymax>
		</bndbox>
	</object>
</annotation>
