<annotation>
	<folder>splitted_BIDV_data_6</folder>
	<filename>30ba79f5-3edc-4d9f-a1c3-75c87cb31755.jpg</filename>
	<path>/home/lynkenion/Downloads/splitted_BIDV_data_6/30ba79f5-3edc-4d9f-a1c3-75c87cb31755.jpg</path>
	<source>
		<database>Unknown</database>
	</source>
	<size>
		<width>67</width>
		<height>257</height>
		<depth>3</depth>
	</size>
	<segmented>0</segmented>
	<object>
		<name>Lanyard</name>
		<pose>Unspecified</pose>
		<truncated>0</truncated>
		<difficult>0</difficult>
		<bndbox>
			<xmin>30</xmin>
			<ymin>42</ymin>
			<xmax>51</xmax>
			<ymax>78</ymax>
		</bndbox>
	</object>
</annotation>
