<annotation>
	<folder>splitted_BIDV_data_6</folder>
	<filename>31cd9602-6f2d-4bec-9e6b-c97e29d4cc11.jpg</filename>
	<path>/home/lynkenion/Downloads/splitted_BIDV_data_6/31cd9602-6f2d-4bec-9e6b-c97e29d4cc11.jpg</path>
	<source>
		<database>Unknown</database>
	</source>
	<size>
		<width>109</width>
		<height>206</height>
		<depth>3</depth>
	</size>
	<segmented>0</segmented>
	<object>
		<name>Lanyard</name>
		<pose>Unspecified</pose>
		<truncated>0</truncated>
		<difficult>0</difficult>
		<bndbox>
			<xmin>54</xmin>
			<ymin>80</ymin>
			<xmax>96</xmax>
			<ymax>160</ymax>
		</bndbox>
	</object>
	<object>
		<name>ID_CARD</name>
		<pose>Unspecified</pose>
		<truncated>0</truncated>
		<difficult>0</difficult>
		<bndbox>
			<xmin>77</xmin>
			<ymin>159</ymin>
			<xmax>93</xmax>
			<ymax>190</ymax>
		</bndbox>
	</object>
</annotation>
