<annotation>
	<folder>splitted_BIDV_data_6</folder>
	<filename>31f13a53-0974-49a3-a544-e0b6fec237d0.jpg</filename>
	<path>/home/lynkenion/Downloads/splitted_BIDV_data_6/31f13a53-0974-49a3-a544-e0b6fec237d0.jpg</path>
	<source>
		<database>Unknown</database>
	</source>
	<size>
		<width>197</width>
		<height>548</height>
		<depth>3</depth>
	</size>
	<segmented>0</segmented>
	<object>
		<name>Lanyard</name>
		<pose>Unspecified</pose>
		<truncated>0</truncated>
		<difficult>0</difficult>
		<bndbox>
			<xmin>57</xmin>
			<ymin>80</ymin>
			<xmax>144</xmax>
			<ymax>192</ymax>
		</bndbox>
	</object>
	<object>
		<name>ID_CARD</name>
		<pose>Unspecified</pose>
		<truncated>0</truncated>
		<difficult>0</difficult>
		<bndbox>
			<xmin>77</xmin>
			<ymin>200</ymin>
			<xmax>135</xmax>
			<ymax>275</ymax>
		</bndbox>
	</object>
</annotation>
